rayvision_utils/__init__.py
rayvision_utils/analyse_handle.py
rayvision_utils/cmd.py
rayvision_utils/constants.py
rayvision_utils/json_handle.py
rayvision_utils/utils.py
rayvision_utils/exception/__init__.py
rayvision_utils/exception/error_msg.py
rayvision_utils/exception/exception.py
rayvision_utils/exception/tips.py
rayvision_utils/exception/tips_code.py
rayvision_utils/tests/__init__.py
rayvision_utils/tests/conftest.py
rayvision_utils/tests/test_analyze_handle.py
rayvision_utils/tests/test_cmd.py
rayvision_utils/tests/test_exception.py
rayvision_utils/tests/test_json_handle.py
rayvision_utils/tests/test_tips.py
rayvision_utils/tests/test_utils.py
ray_test-0.1.9.dist-info/METADATA
ray_test-0.1.9.dist-info/WHEEL
ray_test-0.1.9.dist-info/top_level.txt
ray_test-0.1.9.dist-info/RECORD
