Metadata-Version: 2.1
Name: ray-test
Version: 0.1.9
Summary: A Python API for Using Renderbus cloud rendering.
Home-page: https://github.com/renderbus/rayvision_utils
Author: Shenzhen Rayvision Technology Co., Ltd
Author-email: developer@rayvision.com
License: UNKNOWN
Platform: UNKNOWN
Classifier: Programming Language :: Python
Classifier: Programming Language :: Python :: 2
Classifier: Programming Language :: Python :: 3
Requires-Python: >=2.7.10,>=3.6.0
Requires-Dist: rayvision-log
Requires-Dist: rayvision-api
Requires-Dist: future
Requires-Dist: requests
Requires-Dist: tenacity
